slack_qna/__init__.py
slack_qna/schema.py
slack_qna/slack_qna.py
slack_qna-0.1.1.dist-info/LICENSE
slack_qna-0.1.1.dist-info/METADATA
slack_qna-0.1.1.dist-info/WHEEL
slack_qna-0.1.1.dist-info/RECORD
