Metadata-Version: 2.1
Name: slack-qna
Version: 0.1.1
Summary: An easy plug-and-use library for developing Slack BOT that serves a Q&A-like use case.
Author: lokwkin
Author-email: lokwkin@gmail.com
Requires-Python: >=3.11,<4.0
Classifier: Programming Language :: Python :: 3
Classifier: Programming Language :: Python :: 3.11
Classifier: Programming Language :: Python :: 3.12
Requires-Dist: slack-bolt (>=1.18.1,<2.0.0)
Requires-Dist: slack-sdk (>=3.26.0,<4.0.0)
